lightwhisperstt/__init__.py
lightwhisperstt/core.py
lightwhisperstt-0.1.2.dist-info/licenses/LICENSE
lightwhisperstt-0.1.2.dist-info/METADATA
lightwhisperstt-0.1.2.dist-info/WHEEL
lightwhisperstt-0.1.2.dist-info/top_level.txt
lightwhisperstt-0.1.2.dist-info/RECORD
