Metadata-Version: 2.4
Name: lightwhisperstt
Version: 0.1.2
Summary: Lightweight near real-time offline STT using Whisper + VAD
Author-email: Kavan00 <kavan00@proton.me>
License: MIT
Project-URL: Homepage, https://github.com/Kavan00/LightWhisperSTT
Project-URL: Source, https://github.com/Kavan00/LightWhisperSTT
Requires-Python: >=3.10
License-File: LICENSE
Requires-Dist: numpy
Requires-Dist: sounddevice
Requires-Dist: webrtcvad
Requires-Dist: pywhispercpp
Requires-Dist: librosa
Dynamic: license-file
